strvcf_annotator/__init__.py
strvcf_annotator/api.py
strvcf_annotator/cli.py
strvcf_annotator/core/__init__.py
strvcf_annotator/core/annotation.py
strvcf_annotator/core/repeat_utils.py
strvcf_annotator/core/str_reference.py
strvcf_annotator/core/vcf_processor.py
strvcf_annotator/parsers/__init__.py
strvcf_annotator/parsers/base.py
strvcf_annotator/parsers/generic.py
strvcf_annotator/utils/__init__.py
strvcf_annotator/utils/validation.py
strvcf_annotator/utils/vcf_utils.py
strvcf_annotator-0.2.2.dist-info/licenses/LICENSE
strvcf_annotator-0.2.2.dist-info/METADATA
strvcf_annotator-0.2.2.dist-info/WHEEL
strvcf_annotator-0.2.2.dist-info/entry_points.txt
strvcf_annotator-0.2.2.dist-info/top_level.txt
strvcf_annotator-0.2.2.dist-info/RECORD
