Metadata-Version: 2.4
Name: strvcf-annotator
Version: 0.2.2
Summary: STR annotation tool for VCF files
Home-page: https://github.com/acg-team/strvcf_annotator
Author: Olesia Kondrateva
Author-email: Olesia Kondrateva <xkdnoa@gmail.com>
License: MIT
Project-URL: Homepage, https://github.com/acg-team/strvcf_annotator
Project-URL: Repository, https://github.com/acg-team/strvcf_annotator
Project-URL: Documentation, https://github.com/acg-team/strvcf_annotator/#readme
Project-URL: Bug Tracker, https://github.com/acg-team/strvcf_annotator/issues
Keywords: strvcf,vcf,str,annotation,bioinformatics,genomics
Classifier: Development Status :: 2 - Pre-Alpha
Classifier: Intended Audience :: Developers
Classifier: Intended Audience :: Science/Research
Classifier: License :: OSI Approved :: MIT License
Classifier: Natural Language :: English
Classifier: Operating System :: OS Independent
Classifier: Programming Language :: Python :: 3
Classifier: Programming Language :: Python :: 3.8
Classifier: Programming Language :: Python :: 3.9
Classifier: Programming Language :: Python :: 3.10
Classifier: Programming Language :: Python :: 3.11
Classifier: Programming Language :: Python :: 3.12
Classifier: Topic :: Scientific/Engineering :: Bio-Informatics
Requires-Python: >=3.8
License-File: LICENSE
Requires-Dist: pysam>=0.22.0
Requires-Dist: pandas>=2.0.0
Provides-Extra: dev
Requires-Dist: pytest>=8.0.0; extra == "dev"
Requires-Dist: pytest-cov>=4.1.0; extra == "dev"
Requires-Dist: ruff>=0.3.5; extra == "dev"
Requires-Dist: tox>=4.0.0; extra == "dev"
Requires-Dist: coverage>=7.0.0; extra == "dev"
Requires-Dist: Sphinx>=7.2.6; extra == "dev"
Requires-Dist: twine>=4.0.0; extra == "dev"
Requires-Dist: bump2version>=1.0.1; extra == "dev"
Requires-Dist: watchdog>=3.0.0; extra == "dev"
Dynamic: author
Dynamic: home-page
Dynamic: license-file
Dynamic: requires-python
